Classfile /E:/__PROJECT__/JAVA/BookShildt_002/out/production/BookShildt_002/e0084_Annotations_3/Meta3.class
  Last modified 2 ����. 2023 �.; size 1946 bytes
  SHA-256 checksum 33413242666d68ea7ebfc8948a4b995fd657e8544cc023c33e471c80f93cf87e
  Compiled from "Meta3.java"
public class e0084_Annotations_3.Meta3
  minor version: 0
  major version: 61
  flags: (0x0021) ACC_PUBLIC, ACC_SUPER
  this_class: #7                          // e0084_Annotations_3/Meta3
  super_class: #2                         // java/lang/Object
  interfaces: 0, fields: 0, methods: 3, attributes: 2
Constant pool:
   #1 = Methodref          #2.#3          // java/lang/Object."<init>":()V
   #2 = Class              #4             // java/lang/Object
   #3 = NameAndType        #5:#6          // "<init>":()V
   #4 = Utf8               java/lang/Object
   #5 = Utf8               <init>
   #6 = Utf8               ()V
   #7 = Class              #8             // e0084_Annotations_3/Meta3
   #8 = Utf8               e0084_Annotations_3/Meta3
   #9 = Methodref          #7.#3          // e0084_Annotations_3/Meta3."<init>":()V
  #10 = Methodref          #2.#11         // java/lang/Object.getClass:()Ljava/lang/Class;
  #11 = NameAndType        #12:#13        // getClass:()Ljava/lang/Class;
  #12 = Utf8               getClass
  #13 = Utf8               ()Ljava/lang/Class;
  #14 = Methodref          #15.#16        // java/lang/Class.getAnnotations:()[Ljava/lang/annotation/Annotation;
  #15 = Class              #17            // java/lang/Class
  #16 = NameAndType        #18:#19        // getAnnotations:()[Ljava/lang/annotation/Annotation;
  #17 = Utf8               java/lang/Class
  #18 = Utf8               getAnnotations
  #19 = Utf8               ()[Ljava/lang/annotation/Annotation;
  #20 = Fieldref           #21.#22        // java/lang/System.out:Ljava/io/PrintStream;
  #21 = Class              #23            // java/lang/System
  #22 = NameAndType        #24:#25        // out:Ljava/io/PrintStream;
  #23 = Utf8               java/lang/System
  #24 = Utf8               out
  #25 = Utf8               Ljava/io/PrintStream;
  #26 = String             #27            // ALL ANNOTATIONS FOR CLASS META3:
  #27 = Utf8               ALL ANNOTATIONS FOR CLASS META3:
  #28 = Methodref          #29.#30        // java/io/PrintStream.println:(Ljava/lang/String;)V
  #29 = Class              #31            // java/io/PrintStream
  #30 = NameAndType        #32:#33        // println:(Ljava/lang/String;)V
  #31 = Utf8               java/io/PrintStream
  #32 = Utf8               println
  #33 = Utf8               (Ljava/lang/String;)V
  #34 = Methodref          #29.#35        // java/io/PrintStream.println:(Ljava/lang/Object;)V
  #35 = NameAndType        #32:#36        // println:(Ljava/lang/Object;)V
  #36 = Utf8               (Ljava/lang/Object;)V
  #37 = Methodref          #29.#38        // java/io/PrintStream.println:()V
  #38 = NameAndType        #32:#6         // println:()V
  #39 = String             #40            // myMeth
  #40 = Utf8               myMeth
  #41 = Methodref          #15.#42        // java/lang/Class.getMethod:(Ljava/lang/String;[Ljava/lang/Class;)Ljava/lang/reflect/Method;
  #42 = NameAndType        #43:#44        // getMethod:(Ljava/lang/String;[Ljava/lang/Class;)Ljava/lang/reflect/Method;
  #43 = Utf8               getMethod
  #44 = Utf8               (Ljava/lang/String;[Ljava/lang/Class;)Ljava/lang/reflect/Method;
  #45 = Methodref          #46.#16        // java/lang/reflect/Method.getAnnotations:()[Ljava/lang/annotation/Annotation;
  #46 = Class              #47            // java/lang/reflect/Method
  #47 = Utf8               java/lang/reflect/Method
  #48 = String             #49            // ALL ANNOTATIONS FOR METHOS myMeth():
  #49 = Utf8               ALL ANNOTATIONS FOR METHOS myMeth():
  #50 = Class              #51            // java/lang/NoSuchMethodException
  #51 = Utf8               java/lang/NoSuchMethodException
  #52 = Fieldref           #21.#53        // java/lang/System.err:Ljava/io/PrintStream;
  #53 = NameAndType        #54:#25        // err:Ljava/io/PrintStream;
  #54 = Utf8               err
  #55 = String             #56            // Method not found!!!!!!!!!!!!!!!
  #56 = Utf8               Method not found!!!!!!!!!!!!!!!
  #57 = Methodref          #50.#58        // java/lang/NoSuchMethodException.printStackTrace:()V
  #58 = NameAndType        #59:#6         // printStackTrace:()V
  #59 = Utf8               printStackTrace
  #60 = Methodref          #7.#61         // e0084_Annotations_3/Meta3.myMeth:()V
  #61 = NameAndType        #40:#6         // myMeth:()V
  #62 = Utf8               Code
  #63 = Utf8               LineNumberTable
  #64 = Utf8               LocalVariableTable
  #65 = Utf8               this
  #66 = Utf8               Le0084_Annotations_3/Meta3;
  #67 = Utf8               a
  #68 = Utf8               Ljava/lang/annotation/Annotation;
  #69 = Utf8               annos
  #70 = Utf8               [Ljava/lang/annotation/Annotation;
  #71 = Utf8               m
  #72 = Utf8               Ljava/lang/reflect/Method;
  #73 = Utf8               e
  #74 = Utf8               Ljava/lang/NoSuchMethodException;
  #75 = Utf8               obj
  #76 = Utf8               StackMapTable
  #77 = Class              #70            // "[Ljava/lang/annotation/Annotation;"
  #78 = Utf8               RuntimeVisibleAnnotations
  #79 = Utf8               Le0084_Annotations_3/What;
  #80 = Utf8               description
  #81 = Utf8               IT IS ANNOTATION OF TEST METHOD
  #82 = Utf8               Le0082_Annotations/MyAnno;
  #83 = Utf8               str
  #84 = Utf8               Anno for Method myMeth
  #85 = Utf8               val
  #86 = Integer            122
  #87 = Utf8               main
  #88 = Utf8               ([Ljava/lang/String;)V
  #89 = Utf8               args
  #90 = Utf8               [Ljava/lang/String;
  #91 = Utf8               SourceFile
  #92 = Utf8               Meta3.java
  #93 = Utf8               IT IS ANNOTATION OF TEST CLASS
  #94 = Utf8               Anno for class Metta 3
  #95 = Integer            111
{
  public e0084_Annotations_3.Meta3();
    descriptor: ()V
    flags: (0x0001) ACC_PUBLIC
    Code:
      stack=1, locals=1, args_size=1
         0: aload_0
         1: invokespecial #1                  // Method java/lang/Object."<init>":()V
         4: return
      LineNumberTable:
        line 10: 0
      LocalVariableTable:
        Start  Length  Slot  Name   Signature
            0       5     0  this   Le0084_Annotations_3/Meta3;

  public static void myMeth();
    descriptor: ()V
    flags: (0x0009) ACC_PUBLIC, ACC_STATIC
    Code:
      stack=3, locals=7, args_size=0
         0: new           #7                  // class e0084_Annotations_3/Meta3
         3: dup
         4: invokespecial #9                  // Method "<init>":()V
         7: astore_0
         
         8: aload_0
         9: invokevirtual #10                 // Method java/lang/Object.getClass:()Ljava/lang/Class;
        12: invokevirtual #14                 // Method java/lang/Class.getAnnotations:()[Ljava/lang/annotation/Annotation;
        15: astore_1
        16: getstatic     #20                 // Field java/lang/System.out:Ljava/io/PrintStream;
        19: ldc           #26                 // String ALL ANNOTATIONS FOR CLASS META3:
        21: invokevirtual #28                 // Method java/io/PrintStream.println:(Ljava/lang/String;)V
        24: aload_1
        25: astore_2
        26: aload_2
        27: arraylength
        28: istore_3
        29: iconst_0
        30: istore        4
        32: iload         4
        34: iload_3
        35: if_icmpge     58
        38: aload_2
        39: iload         4
        41: aaload
        42: astore        5
        
        44: getstatic     #20                 // Field java/lang/System.out:Ljava/io/PrintStream;
        47: aload         5
        49: invokevirtual #34                 // Method java/io/PrintStream.println:(Ljava/lang/Object;)V
        52: iinc          4, 1
        55: goto          32
        
        58: getstatic     #20                 // Field java/lang/System.out:Ljava/io/PrintStream;
        61: invokevirtual #37                 // Method java/io/PrintStream.println:()V
        64: aload_0
        65: invokevirtual #10                 // Method java/lang/Object.getClass:()Ljava/lang/Class;
        68: ldc           #39                 // String myMeth
        70: iconst_0

        71: anewarray     #15                 // class java/lang/Class
        74: invokevirtual #41                 // Method java/lang/Class.getMethod:(Ljava/lang/String;[Ljava/lang/Class;)Ljava/lang/reflect/Method;
        77: astore_2
        
        78: aload_2
        79: invokevirtual #45                 // Method java/lang/reflect/Method.getAnnotations:()[Ljava/lang/annotation/Annotation;
        82: astore_1
        
        83: getstatic     #20                 // Field java/lang/System.out:Ljava/io/PrintStream;
        86: ldc           #48                 // String ALL ANNOTATIONS FOR METHOS myMeth():
        88: invokevirtual #28                 // Method java/io/PrintStream.println:(Ljava/lang/String;)V

        91: aload_1
        92: astore_3
        93: aload_3
        94: arraylength
        95: istore        4
        97: iconst_0
        98: istore        5
        
       100: iload         5
       102: iload         4
       104: if_icmpge     127
       107: aload_3
       108: iload         5
       110: aaload
       111: astore        6
       113: getstatic     #20                 // Field java/lang/System.out:Ljava/io/PrintStream;
       116: aload         6
       118: invokevirtual #34                 // Method java/io/PrintStream.println:(Ljava/lang/Object;)V
       121: iinc          5, 1
       124: goto          100
       127: goto          151
       
       130: astore_1

       131: getstatic     #52                 // Field java/lang/System.err:Ljava/io/PrintStream;
       134: ldc           #55                 // String Method not found!!!!!!!!!!!!!!!
       136: invokevirtual #28                 // Method java/io/PrintStream.println:(Ljava/lang/String;)V
       139: aload_1
       140: invokevirtual #57                 // Method java/lang/NoSuchMethodException.printStackTrace:()V
       143: getstatic     #52                 // Field java/lang/System.err:Ljava/io/PrintStream;
       146: ldc           #55                 // String Method not found!!!!!!!!!!!!!!!
       148: invokevirtual #28                 // Method java/io/PrintStream.println:(Ljava/lang/String;)V
       
       151: return
      Exception table:
         from    to  target type
             8   127   130   Class java/lang/NoSuchMethodException
      LineNumberTable:
        line 15: 0
        line 18: 8
        line 20: 16
        line 21: 24
        line 22: 44
        line 21: 52
        line 24: 58
        line 26: 64
        line 27: 78
        line 29: 83
        line 30: 91
        line 31: 113
        line 30: 121
        line 38: 127
        line 34: 130
        line 35: 131
        line 36: 139
        line 37: 143
        line 39: 151
      LocalVariableTable:
        Start  Length  Slot  Name   Signature
           44       8     5     a   Ljava/lang/annotation/Annotation;
          113       8     6     a   Ljava/lang/annotation/Annotation;
           16     111     1 annos   [Ljava/lang/annotation/Annotation;
           78      49     2     m   Ljava/lang/reflect/Method;
          131      20     1     e   Ljava/lang/NoSuchMethodException;
            8     144     0   obj   Le0084_Annotations_3/Meta3;
      StackMapTable: number_of_entries = 6
        frame_type = 255 /* full_frame */  
          offset_delta = 32
          locals = [ class e0084_Annotations_3/Meta3, class "[Ljava/lang/annotation/Annotation;", class "[Ljava/lang/annotation/Annotation;", int, int ]
          stack = []
        frame_type = 248 /* chop */  
          offset_delta = 25
        frame_type = 255 /* full_frame */  
          offset_delta = 41
          locals = [ class e0084_Annotations_3/Meta3, class "[Ljava/lang/annotation/Annotation;", class java/lang/reflect/Method, class "[Ljava/lang/annotation/Annotation;", int, int ]
          stack = []
        frame_type = 255 /* full_frame */  
          offset_delta = 26
          locals = [ class e0084_Annotations_3/Meta3 ]
          stack = []
        frame_type = 66 /* same_locals_1_stack_item */ 
          stack = [ class java/lang/NoSuchMethodException ]
        frame_type = 20 /* same */ 
    RuntimeVisibleAnnotations:
      0: #79(#80=s#81)
        e0084_Annotations_3.What(
          description="IT IS ANNOTATION OF TEST METHOD"
        )
      1: #82(#83=s#84,#85=I#86)
        e0082_Annotations.MyAnno(
          str="Anno for Method myMeth"
          val=122
        )

  public static void main(java.lang.String[]);
    descriptor: ([Ljava/lang/String;)V
    flags: (0x0009) ACC_PUBLIC, ACC_STATIC
    Code:
      stack=0, locals=1, args_size=1
         0: invokestatic  #60                 // Method myMeth:()V
         3: return
      LineNumberTable:
        line 42: 0
        line 43: 3
      LocalVariableTable:
        Start  Length  Slot  Name   Signature
            0       4     0  args   [Ljava/lang/String;
}
SourceFile: "Meta3.java"
RuntimeVisibleAnnotations:
  0: #79(#80=s#93)
    e0084_Annotations_3.What(
      description="IT IS ANNOTATION OF TEST CLASS"
    )
  1: #82(#83=s#94,#85=I#95)
    e0082_Annotations.MyAnno(
      str="Anno for class Metta 3"
      val=111
    )
#############################################################################################
package e0084_Annotations_3;

import e0082_Annotations.MyAnno;

import java.lang.annotation.Annotation;
import java.lang.reflect.Method;

@What(description = "IT IS ANNOTATION OF TEST CLASS")
@MyAnno(str = "Anno for class Metta 3", val = 111)
public class Meta3 {

    @What(description = "IT IS ANNOTATION OF TEST METHOD")
    @MyAnno(str = "Anno for Method myMeth", val = 122)
    public static void myMeth() {
        Meta3 obj = new Meta3();

        try {
            Annotation annos[] = obj.getClass().getAnnotations();

            System.out.println("ALL ANNOTATIONS FOR CLASS META3:");
            for (Annotation a : annos) {
                System.out.println(a);
            }
            System.out.println();

            Method m = obj.getClass().getMethod("myMeth");
            annos = m.getAnnotations();

            System.out.println("ALL ANNOTATIONS FOR METHOS myMeth():");
            for (Annotation a : annos) {
                System.out.println(a);
            }

        } catch (NoSuchMethodException e) {
            System.err.println("Method not found!!!!!!!!!!!!!!!");
            e.printStackTrace();
            System.err.println("Method not found!!!!!!!!!!!!!!!");
        }
    }

    public static void main(String[] args) {
        myMeth();
    }
}
---------------------------------------------------------------------------------------------
