Classfile /E:/__PROJECT__/JAVA/BookShildt_002/out/production/BookShildt_002/e0083_Annotations_2/Meta2.class
  Last modified 2 ����. 2023 �.; size 2129 bytes
  SHA-256 checksum ee2506adcee57d51bb9e1af150a4ae0feeb11d55faaf4a9ca80e91aa0dc86d66
  Compiled from "Meta2.java"
public class e0083_Annotations_2.Meta2
  minor version: 0
  major version: 61
  flags: (0x0021) ACC_PUBLIC, ACC_SUPER
  this_class: #7                          // e0083_Annotations_2/Meta2
  super_class: #2                         // java/lang/Object
  interfaces: 0, fields: 0, methods: 3, attributes: 3
Constant pool:
    #1 = Methodref          #2.#3         // java/lang/Object."<init>":()V
    #2 = Class              #4            // java/lang/Object
    #3 = NameAndType        #5:#6         // "<init>":()V
    #4 = Utf8               java/lang/Object
    #5 = Utf8               <init>
    #6 = Utf8               ()V
    #7 = Class              #8            // e0083_Annotations_2/Meta2
    #8 = Utf8               e0083_Annotations_2/Meta2
    #9 = Methodref          #7.#3         // e0083_Annotations_2/Meta2."<init>":()V
   #10 = Methodref          #2.#11        // java/lang/Object.getClass:()Ljava/lang/Class;
   #11 = NameAndType        #12:#13       // getClass:()Ljava/lang/Class;
   #12 = Utf8               getClass
   #13 = Utf8               ()Ljava/lang/Class;
   #14 = String             #15           // myMeth
   #15 = Utf8               myMeth
   #16 = Class              #17           // java/lang/Class
   #17 = Utf8               java/lang/Class
   #18 = Class              #19           // java/lang/String
   #19 = Utf8               java/lang/String
   #20 = Fieldref           #21.#22       // java/lang/Integer.TYPE:Ljava/lang/Class;
   #21 = Class              #23           // java/lang/Integer
   #22 = NameAndType        #24:#25       // TYPE:Ljava/lang/Class;
   #23 = Utf8               java/lang/Integer
   #24 = Utf8               TYPE
   #25 = Utf8               Ljava/lang/Class;
   #26 = Methodref          #16.#27       // java/lang/Class.getMethod:(Ljava/lang/String;[Ljava/lang/Class;)Ljava/lang/reflect/Method;
   #27 = NameAndType        #28:#29       // getMethod:(Ljava/lang/String;[Ljava/lang/Class;)Ljava/lang/reflect/Method;
   #28 = Utf8               getMethod
   #29 = Utf8               (Ljava/lang/String;[Ljava/lang/Class;)Ljava/lang/reflect/Method;
   #30 = Class              #31           // e0083_Annotations_2/MyAnno2
   #31 = Utf8               e0083_Annotations_2/MyAnno2
   #32 = Methodref          #33.#34       // java/lang/reflect/Method.getAnnotation:(Ljava/lang/Class;)Ljava/lang/annotation/Annotation;
   #33 = Class              #35           // java/lang/reflect/Method
   #34 = NameAndType        #36:#37       // getAnnotation:(Ljava/lang/Class;)Ljava/lang/annotation/Annotation;
   #35 = Utf8               java/lang/reflect/Method
   #36 = Utf8               getAnnotation
   #37 = Utf8               (Ljava/lang/Class;)Ljava/lang/annotation/Annotation;
   #38 = Fieldref           #39.#40       // java/lang/System.out:Ljava/io/PrintStream;
   #39 = Class              #41           // java/lang/System
   #40 = NameAndType        #42:#43       // out:Ljava/io/PrintStream;
   #41 = Utf8               java/lang/System
   #42 = Utf8               out
   #43 = Utf8               Ljava/io/PrintStream;
   #44 = InterfaceMethodref #30.#45       // e0083_Annotations_2/MyAnno2.str:()Ljava/lang/String;
   #45 = NameAndType        #46:#47       // str:()Ljava/lang/String;
   #46 = Utf8               str
   #47 = Utf8               ()Ljava/lang/String;
   #48 = InterfaceMethodref #30.#49       // e0083_Annotations_2/MyAnno2.val:()I
   #49 = NameAndType        #50:#51       // val:()I
   #50 = Utf8               val
   #51 = Utf8               ()I
   #52 = InvokeDynamic      #0:#53        // #0:makeConcatWithConstants:(Ljava/lang/String;I)Ljava/lang/String;
   #53 = NameAndType        #54:#55       // makeConcatWithConstants:(Ljava/lang/String;I)Ljava/lang/String;
   #54 = Utf8               makeConcatWithConstants
   #55 = Utf8               (Ljava/lang/String;I)Ljava/lang/String;
   #56 = Methodref          #57.#58       // java/io/PrintStream.println:(Ljava/lang/String;)V
   #57 = Class              #59           // java/io/PrintStream
   #58 = NameAndType        #60:#61       // println:(Ljava/lang/String;)V
   #59 = Utf8               java/io/PrintStream
   #60 = Utf8               println
   #61 = Utf8               (Ljava/lang/String;)V
   #62 = Class              #63           // java/lang/NoSuchMethodException
   #63 = Utf8               java/lang/NoSuchMethodException
   #64 = Methodref          #62.#65       // java/lang/NoSuchMethodException.printStackTrace:()V
   #65 = NameAndType        #66:#6        // printStackTrace:()V
   #66 = Utf8               printStackTrace
   #67 = String             #68           // TEST
   #68 = Utf8               TEST
   #69 = Methodref          #7.#70        // e0083_Annotations_2/Meta2.myMeth:(Ljava/lang/String;I)V
   #70 = NameAndType        #15:#71       // myMeth:(Ljava/lang/String;I)V
   #71 = Utf8               (Ljava/lang/String;I)V
   #72 = Utf8               Code
   #73 = Utf8               LineNumberTable
   #74 = Utf8               LocalVariableTable
   #75 = Utf8               this
   #76 = Utf8               Le0083_Annotations_2/Meta2;
   #77 = Utf8               cl
   #78 = Utf8               meth
   #79 = Utf8               Ljava/lang/reflect/Method;
   #80 = Utf8               anno
   #81 = Utf8               Le0083_Annotations_2/MyAnno2;
   #82 = Utf8               e
   #83 = Utf8               Ljava/lang/NoSuchMethodException;
   #84 = Utf8               Ljava/lang/String;
   #85 = Utf8               i
   #86 = Utf8               I
   #87 = Utf8               ob
   #88 = Utf8               LocalVariableTypeTable
   #89 = Utf8               Ljava/lang/Class<*>;
   #90 = Utf8               StackMapTable
   #91 = Utf8               RuntimeVisibleAnnotations
   #92 = Utf8               TWO PARAMETERS
   #93 = Integer            89
   #94 = Utf8               main
   #95 = Utf8               ([Ljava/lang/String;)V
   #96 = Utf8               args
   #97 = Utf8               [Ljava/lang/String;
   #98 = Utf8               SourceFile
   #99 = Utf8               Meta2.java
  #100 = Utf8               BootstrapMethods
  #101 = MethodHandle       6:#102        // REF_invokeStatic java/lang/invoke/StringConcatFactory.makeConcatWithConstants:(Ljava/lang/invoke/MethodHandles$Lookup;Ljava/lang/String;Ljava/lang/invoke/MethodType;Ljava/lang/String;[Ljava/lang/Object;)Ljava/lang/invoke/CallSite;
  #102 = Methodref          #103.#104     // java/lang/invoke/StringConcatFactory.makeConcatWithConstants:(Ljava/lang/invoke/MethodHandles$Lookup;Ljava/lang/String;Ljava/lang/invoke/MethodType;Ljava/lang/String;[Ljava/lang/Object;)Ljava/lang/invoke/CallSite;
  #103 = Class              #105          // java/lang/invoke/StringConcatFactory
  #104 = NameAndType        #54:#106      // makeConcatWithConstants:(Ljava/lang/invoke/MethodHandles$Lookup;Ljava/lang/String;Ljava/lang/invoke/MethodType;Ljava/lang/String;[Ljava/lang/Object;)Ljava/lang/invoke/CallSite;
  #105 = Utf8               java/lang/invoke/StringConcatFactory
  #106 = Utf8               (Ljava/lang/invoke/MethodHandles$Lookup;Ljava/lang/String;Ljava/lang/invoke/MethodType;Ljava/lang/String;[Ljava/lang/Object;)Ljava/lang/invoke/CallSite;
  #107 = String             #108          // \u0001 \u0001
  #108 = Utf8               \u0001 \u0001
  #109 = Utf8               InnerClasses
  #110 = Class              #111          // java/lang/invoke/MethodHandles$Lookup
  #111 = Utf8               java/lang/invoke/MethodHandles$Lookup
  #112 = Class              #113          // java/lang/invoke/MethodHandles
  #113 = Utf8               java/lang/invoke/MethodHandles
  #114 = Utf8               Lookup
{
  public e0083_Annotations_2.Meta2();
    descriptor: ()V
    flags: (0x0001) ACC_PUBLIC
    Code:
      stack=1, locals=1, args_size=1
         0: aload_0
         1: invokespecial #1                  // Method java/lang/Object."<init>":()V
         4: return
      LineNumberTable:
        line 5: 0
      LocalVariableTable:
        Start  Length  Slot  Name   Signature
            0       5     0  this   Le0083_Annotations_2/Meta2;

  public static void myMeth(java.lang.String, int);
    descriptor: (Ljava/lang/String;I)V
    flags: (0x0009) ACC_PUBLIC, ACC_STATIC
    Code:
      stack=6, locals=6, args_size=2
         0: new           #7                  // class e0083_Annotations_2/Meta2
         3: dup
         4: invokespecial #9                  // Method "<init>":()V
         7: astore_2

         8: aload_2
         9: invokevirtual #10                 // Method java/lang/Object.getClass:()Ljava/lang/Class;
        12: astore_3

        13: aload_3
        14: ldc           #14                 // String myMeth
        16: iconst_2
        17: anewarray     #16                 // class java/lang/Class
        20: dup
        21: iconst_0
        22: ldc           #18                 // class java/lang/String
        24: aastore
        25: dup
        26: iconst_1
        27: getstatic     #20                 // Field java/lang/Integer.TYPE:Ljava/lang/Class;
        30: aastore
        31: invokevirtual #26                 // Method java/lang/Class.getMethod:(Ljava/lang/String;[Ljava/lang/Class;)Ljava/lang/reflect/Method;
        34: astore        4

        36: aload         4
        38: ldc           #30                 // class e0083_Annotations_2/MyAnno2
        40: invokevirtual #32                 // Method java/lang/reflect/Method.getAnnotation:(Ljava/lang/Class;)Ljava/lang/annotation/Annotation;
        43: checkcast     #30                 // class e0083_Annotations_2/MyAnno2
        46: astore        5

        48: getstatic     #38                 // Field java/lang/System.out:Ljava/io/PrintStream;
        51: aload         5
        53: invokeinterface #44,  1           // InterfaceMethod e0083_Annotations_2/MyAnno2.str:()Ljava/lang/String;
        58: aload         5
        60: invokeinterface #48,  1           // InterfaceMethod e0083_Annotations_2/MyAnno2.val:()I
        65: invokedynamic #52,  0             // InvokeDynamic #0:makeConcatWithConstants:(Ljava/lang/String;I)Ljava/lang/String;
        70: invokevirtual #56                 // Method java/io/PrintStream.println:(Ljava/lang/String;)V
        73: goto          81

        76: astore_3
        77: aload_3
        78: invokevirtual #64                 // Method java/lang/NoSuchMethodException.printStackTrace:()V

        81: return
      Exception table:
         from    to  target type
             8    73    76   Class java/lang/NoSuchMethodException
      LineNumberTable:
        line 8: 0
        line 11: 8
        line 12: 13
        line 14: 36
        line 16: 48
        line 20: 73
        line 18: 76
        line 19: 77
        line 21: 81
      LocalVariableTable:
        Start  Length  Slot  Name   Signature
           13      60     3    cl   Ljava/lang/Class;
           36      37     4  meth   Ljava/lang/reflect/Method;
           48      25     5  anno   Le0083_Annotations_2/MyAnno2;
           77       4     3     e   Ljava/lang/NoSuchMethodException;
            0      82     0   str   Ljava/lang/String;
            0      82     1     i   I
            8      74     2    ob   Le0083_Annotations_2/Meta2;
      LocalVariableTypeTable:
        Start  Length  Slot  Name   Signature
           13      60     3    cl   Ljava/lang/Class<*>;
      StackMapTable: number_of_entries = 2
        frame_type = 255 /* full_frame */ 
          offset_delta = 76
          locals = [ class java/lang/String, int, class e0083_Annotations_2/Meta2 ]
          stack = [ class java/lang/NoSuchMethodException ]
        frame_type = 4 /* same */ 
    RuntimeVisibleAnnotations:
      0: #81(#46=s#92,#50=I#93)
        e0083_Annotations_2.MyAnno2(
          str="TWO PARAMETERS"
          val=89
        )

  public static void main(java.lang.String[]);
    descriptor: ([Ljava/lang/String;)V
    flags: (0x0009) ACC_PUBLIC, ACC_STATIC
    Code:
      stack=2, locals=1, args_size=1
         0: ldc           #67                 // String TEST
         2: bipush        22
         4: invokestatic  #69                 // Method myMeth:(Ljava/lang/String;I)V
         7: return
      LineNumberTable:
        line 24: 0
        line 25: 7
      LocalVariableTable:
        Start  Length  Slot  Name   Signature
            0       8     0  args   [Ljava/lang/String;
}
SourceFile: "Meta2.java"
BootstrapMethods:
  0: #101 REF_invokeStatic java/lang/invoke/StringConcatFactory.makeConcatWithConstants:(Ljava/lang/invoke/MethodHandles$Lookup;Ljava/lang/String;Ljava/lang/invoke/MethodType;Ljava/lang/String;[Ljava/lang/Object;)Ljava/lang/invoke/CallSite;
    Method arguments:
      #107 \u0001 \u0001
InnerClasses:
  public static final #114= #110 of #112; // Lookup=class java/lang/invoke/MethodHandles$Lookup of class java/lang/invoke/MethodHandles
#############################################################################################
package e0083_Annotations_2;

import java.lang.reflect.Method;

public class Meta2 {
    @MyAnno2(str = "TWO PARAMETERS", val = 89)
    public static void myMeth(String str, int i) {
        Meta2 ob = new Meta2();

        try {
            Class<?> cl = ob.getClass();
            Method meth = cl.getMethod("myMeth", String.class, int.class);

            MyAnno2 anno = meth.getAnnotation(MyAnno2.class);

            System.out.println(anno.str() + " " + anno.val());

        } catch (NoSuchMethodException e) {
            e.printStackTrace();
        }
    }

    public static void main(String[] args) {
        myMeth("TEST", 22);
    }
}
---------------------------------------------------------------------------------------------
