Classfile /E:/__PROJECT__/JAVA/BookShildt_002/out/production/BookShildt_002/e0081_AutoPACK_1/Wrap.class
  Last modified 1 ����. 2023 �.; size 707 bytes
  SHA-256 checksum c9844bf691409201b7af8462e55ded56d22fce0da2470c1eb2f6a350134c05c0
  Compiled from "Wrap.java"
public class e0081_AutoPACK_1.Wrap
  minor version: 0
  major version: 61
  flags: (0x0021) ACC_PUBLIC, ACC_SUPER
  this_class: #28                         // e0081_AutoPACK_1/Wrap
  super_class: #2                         // java/lang/Object
  interfaces: 0, fields: 0, methods: 2, attributes: 1
Constant pool:
   #1 = Methodref          #2.#3          // java/lang/Object."<init>":()V
   #2 = Class              #4             // java/lang/Object
   #3 = NameAndType        #5:#6          // "<init>":()V
   #4 = Utf8               java/lang/Object
   #5 = Utf8               <init>
   #6 = Utf8               ()V
   #7 = Class              #8             // java/lang/Integer
   #8 = Utf8               java/lang/Integer
   #9 = Methodref          #7.#10         // java/lang/Integer."<init>":(I)V
  #10 = NameAndType        #5:#11         // "<init>":(I)V
  #11 = Utf8               (I)V
  #12 = Fieldref           #13.#14        // java/lang/System.out:Ljava/io/PrintStream;
  #13 = Class              #15            // java/lang/System
  #14 = NameAndType        #16:#17        // out:Ljava/io/PrintStream;
  #15 = Utf8               java/lang/System
  #16 = Utf8               out
  #17 = Utf8               Ljava/io/PrintStream;
  #18 = Methodref          #19.#20        // java/io/PrintStream.println:(Ljava/lang/Object;)V
  #19 = Class              #21            // java/io/PrintStream
  #20 = NameAndType        #22:#23        // println:(Ljava/lang/Object;)V
  #21 = Utf8               java/io/PrintStream
  #22 = Utf8               println
  #23 = Utf8               (Ljava/lang/Object;)V
  #24 = Methodref          #7.#25         // java/lang/Integer.valueOf:(I)Ljava/lang/Integer;
  #25 = NameAndType        #26:#27        // valueOf:(I)Ljava/lang/Integer;
  #26 = Utf8               valueOf
  #27 = Utf8               (I)Ljava/lang/Integer;
  #28 = Class              #29            // e0081_AutoPACK_1/Wrap
  #29 = Utf8               e0081_AutoPACK_1/Wrap
  #30 = Utf8               Code
  #31 = Utf8               LineNumberTable
  #32 = Utf8               LocalVariableTable
  #33 = Utf8               this
  #34 = Utf8               Le0081_AutoPACK_1/Wrap;
  #35 = Utf8               main
  #36 = Utf8               ([Ljava/lang/String;)V
  #37 = Utf8               args
  #38 = Utf8               [Ljava/lang/String;
  #39 = Utf8               iOb1
  #40 = Utf8               Ljava/lang/Integer;
  #41 = Utf8               iOb
  #42 = Utf8               SourceFile
  #43 = Utf8               Wrap.java
{
  public e0081_AutoPACK_1.Wrap();
    descriptor: ()V
    flags: (0x0001) ACC_PUBLIC
    Code:
      stack=1, locals=1, args_size=1
         0: aload_0
         1: invokespecial #1                  // Method java/lang/Object."<init>":()V
         4: return
      LineNumberTable:
        line 3: 0
      LocalVariableTable:
        Start  Length  Slot  Name   Signature
            0       5     0  this   Le0081_AutoPACK_1/Wrap;

  public static void main(java.lang.String[]);
    descriptor: ([Ljava/lang/String;)V
    flags: (0x0009) ACC_PUBLIC, ACC_STATIC
    Code:
      stack=3, locals=3, args_size=1
         0: new           #7                  // class java/lang/Integer
         3: dup
         4: bipush        111
         6: invokespecial #9                  // Method java/lang/Integer."<init>":(I)V
         9: astore_1
         
        10: getstatic     #12                 // Field java/lang/System.out:Ljava/io/PrintStream;
        13: aload_1
        14: invokevirtual #18                 // Method java/io/PrintStream.println:(Ljava/lang/Object;)V
        
        17: sipush        222
        20: invokestatic  #24                 // Method java/lang/Integer.valueOf:(I)Ljava/lang/Integer;
        23: astore_2
        
        24: getstatic     #12                 // Field java/lang/System.out:Ljava/io/PrintStream;
        27: aload_2
        28: invokevirtual #18                 // Method java/io/PrintStream.println:(Ljava/lang/Object;)V
        
        31: return
      LineNumberTable:
        line 5: 0
        line 6: 10
        line 8: 17
        line 9: 24
        line 14: 31
      LocalVariableTable:
        Start  Length  Slot  Name   Signature
            0      32     0  args   [Ljava/lang/String;
           10      22     1  iOb1   Ljava/lang/Integer;
           24       8     2   iOb   Ljava/lang/Integer;
}
SourceFile: "Wrap.java"
#############################################################################################
package e0081_AutoPACK_1;

public class Wrap {
    public static void main(String[] args) {
        Integer iOb1 = new Integer(111);
        System.out.println(iOb1);

        Integer iOb = Integer.valueOf(222);
        System.out.println(iOb);

//        int i = iOb.intValue();
//        System.out.printf("iOb1: %s   iOb: %s   i: %s\n", iOb1, iOb, i);

    }
}
---------------------------------------------------------------------------------------------
