Classfile /E:/__PROJECT__/JAVA/BookShildt_002/out/production/BookShildt_002/e0082_Annotations/Meta.class
  Last modified 2 ����. 2023 �.; size 1950 bytes
  SHA-256 checksum 4dc5ee70f0b1ce180c9daf4d6ca07e07211d993c4406376039a1468a20e8690f
  Compiled from "Meta.java"
public class e0082_Annotations.Meta
  minor version: 0
  major version: 61
  flags: (0x0021) ACC_PUBLIC, ACC_SUPER
  this_class: #7                          // e0082_Annotations/Meta
  super_class: #2                         // java/lang/Object
  interfaces: 0, fields: 0, methods: 3, attributes: 3
Constant pool:
    #1 = Methodref          #2.#3         // java/lang/Object."<init>":()V
    #2 = Class              #4            // java/lang/Object
    #3 = NameAndType        #5:#6         // "<init>":()V
    #4 = Utf8               java/lang/Object
    #5 = Utf8               <init>
    #6 = Utf8               ()V
    #7 = Class              #8            // e0082_Annotations/Meta
    #8 = Utf8               e0082_Annotations/Meta
    #9 = Methodref          #7.#3         // e0082_Annotations/Meta."<init>":()V
   #10 = Methodref          #2.#11        // java/lang/Object.getClass:()Ljava/lang/Class;
   #11 = NameAndType        #12:#13       // getClass:()Ljava/lang/Class;
   #12 = Utf8               getClass
   #13 = Utf8               ()Ljava/lang/Class;
   #14 = String             #15           // myMeth
   #15 = Utf8               myMeth
   #16 = Class              #17           // java/lang/Class
   #17 = Utf8               java/lang/Class
   #18 = Methodref          #16.#19       // java/lang/Class.getMethod:(Ljava/lang/String;[Ljava/lang/Class;)Ljava/lang/reflect/Method;
   #19 = NameAndType        #20:#21       // getMethod:(Ljava/lang/String;[Ljava/lang/Class;)Ljava/lang/reflect/Method;
   #20 = Utf8               getMethod
   #21 = Utf8               (Ljava/lang/String;[Ljava/lang/Class;)Ljava/lang/reflect/Method;
   #22 = Class              #23           // e0082_Annotations/MyAnno
   #23 = Utf8               e0082_Annotations/MyAnno
   #24 = Methodref          #25.#26       // java/lang/reflect/Method.getAnnotation:(Ljava/lang/Class;)Ljava/lang/annotation/Annotation;
   #25 = Class              #27           // java/lang/reflect/Method
   #26 = NameAndType        #28:#29       // getAnnotation:(Ljava/lang/Class;)Ljava/lang/annotation/Annotation;
   #27 = Utf8               java/lang/reflect/Method
   #28 = Utf8               getAnnotation
   #29 = Utf8               (Ljava/lang/Class;)Ljava/lang/annotation/Annotation;
   #30 = Fieldref           #31.#32       // java/lang/System.out:Ljava/io/PrintStream;
   #31 = Class              #33           // java/lang/System
   #32 = NameAndType        #34:#35       // out:Ljava/io/PrintStream;
   #33 = Utf8               java/lang/System
   #34 = Utf8               out
   #35 = Utf8               Ljava/io/PrintStream;
   #36 = InterfaceMethodref #22.#37       // e0082_Annotations/MyAnno.str:()Ljava/lang/String;
   #37 = NameAndType        #38:#39       // str:()Ljava/lang/String;
   #38 = Utf8               str
   #39 = Utf8               ()Ljava/lang/String;
   #40 = InterfaceMethodref #22.#41       // e0082_Annotations/MyAnno.val:()I
   #41 = NameAndType        #42:#43       // val:()I
   #42 = Utf8               val
   #43 = Utf8               ()I
   #44 = InvokeDynamic      #0:#45        // #0:makeConcatWithConstants:(Ljava/lang/String;I)Ljava/lang/String;
   #45 = NameAndType        #46:#47       // makeConcatWithConstants:(Ljava/lang/String;I)Ljava/lang/String;
   #46 = Utf8               makeConcatWithConstants
   #47 = Utf8               (Ljava/lang/String;I)Ljava/lang/String;
   #48 = Methodref          #49.#50       // java/io/PrintStream.println:(Ljava/lang/String;)V
   #49 = Class              #51           // java/io/PrintStream
   #50 = NameAndType        #52:#53       // println:(Ljava/lang/String;)V
   #51 = Utf8               java/io/PrintStream
   #52 = Utf8               println
   #53 = Utf8               (Ljava/lang/String;)V
   #54 = Class              #55           // java/lang/NoSuchMethodException
   #55 = Utf8               java/lang/NoSuchMethodException
   #56 = Methodref          #54.#57       // java/lang/NoSuchMethodException.printStackTrace:()V
   #57 = NameAndType        #58:#6        // printStackTrace:()V
   #58 = Utf8               printStackTrace
   #59 = Methodref          #7.#60        // e0082_Annotations/Meta.myMeth:()V
   #60 = NameAndType        #15:#6        // myMeth:()V
   #61 = Utf8               Code
   #62 = Utf8               LineNumberTable
   #63 = Utf8               LocalVariableTable
   #64 = Utf8               this
   #65 = Utf8               Le0082_Annotations/Meta;
   #66 = Utf8               cl
   #67 = Utf8               Ljava/lang/Class;
   #68 = Utf8               meth
   #69 = Utf8               Ljava/lang/reflect/Method;
   #70 = Utf8               anno
   #71 = Utf8               Le0082_Annotations/MyAnno;
   #72 = Utf8               e
   #73 = Utf8               Ljava/lang/NoSuchMethodException;
   #74 = Utf8               ob
   #75 = Utf8               LocalVariableTypeTable
   #76 = Utf8               Ljava/lang/Class<*>;
   #77 = Utf8               StackMapTable
   #78 = Utf8               RuntimeVisibleAnnotations
   #79 = Utf8               EXAMPLE ANNOTATION
   #80 = Integer            111
   #81 = Utf8               main
   #82 = Utf8               ([Ljava/lang/String;)V
   #83 = Utf8               args
   #84 = Utf8               [Ljava/lang/String;
   #85 = Utf8               SourceFile
   #86 = Utf8               Meta.java
   #87 = Utf8               BootstrapMethods
   #88 = MethodHandle       6:#89         // REF_invokeStatic java/lang/invoke/StringConcatFactory.makeConcatWithConstants:(Ljava/lang/invoke/MethodHandles$Lookup;Ljava/lang/String;Ljava/lang/invoke/MethodType;Ljava/lang/String;[Ljava/lang/Object;)Ljava/lang/invoke/CallSite;
   #89 = Methodref          #90.#91       // java/lang/invoke/StringConcatFactory.makeConcatWithConstants:(Ljava/lang/invoke/MethodHandles$Lookup;Ljava/lang/String;Ljava/lang/invoke/MethodType;Ljava/lang/String;[Ljava/lang/Object;)Ljava/lang/invoke/CallSite;
   #90 = Class              #92           // java/lang/invoke/StringConcatFactory
   #91 = NameAndType        #46:#93       // makeConcatWithConstants:(Ljava/lang/invoke/MethodHandles$Lookup;Ljava/lang/String;Ljava/lang/invoke/MethodType;Ljava/lang/String;[Ljava/lang/Object;)Ljava/lang/invoke/CallSite;
   #92 = Utf8               java/lang/invoke/StringConcatFactory
   #93 = Utf8               (Ljava/lang/invoke/MethodHandles$Lookup;Ljava/lang/String;Ljava/lang/invoke/MethodType;Ljava/lang/String;[Ljava/lang/Object;)Ljava/lang/invoke/CallSite;
   #94 = String             #95           // \u0001 \u0001
   #95 = Utf8               \u0001 \u0001
   #96 = Utf8               InnerClasses
   #97 = Class              #98           // java/lang/invoke/MethodHandles$Lookup
   #98 = Utf8               java/lang/invoke/MethodHandles$Lookup
   #99 = Class              #100          // java/lang/invoke/MethodHandles
  #100 = Utf8               java/lang/invoke/MethodHandles
  #101 = Utf8               Lookup
{
  public e0082_Annotations.Meta();
    descriptor: ()V
    flags: (0x0001) ACC_PUBLIC
    Code:
      stack=1, locals=1, args_size=1
         0: aload_0
         1: invokespecial #1                  // Method java/lang/Object."<init>":()V
         4: return
      LineNumberTable:
        line 5: 0
      LocalVariableTable:
        Start  Length  Slot  Name   Signature
            0       5     0  this   Le0082_Annotations/Meta;

  public static void myMeth();
    descriptor: ()V
    flags: (0x0009) ACC_PUBLIC, ACC_STATIC
    Code:
      stack=3, locals=4, args_size=0
         0: new           #7                  // class e0082_Annotations/Meta
         3: dup
         4: invokespecial #9                  // Method "<init>":()V
         7: astore_0

         8: aload_0
         9: invokevirtual #10                 // Method java/lang/Object.getClass:()Ljava/lang/Class;
        12: astore_1
        
        13: aload_1
        14: ldc           #14                 // String myMeth
        16: iconst_0
        17: anewarray     #16                 // class java/lang/Class
        20: invokevirtual #18                 // Method java/lang/Class.getMethod:(Ljava/lang/String;[Ljava/lang/Class;)Ljava/lang/reflect/Method;
        23: astore_2

        24: aload_2
        25: ldc           #22                 // class e0082_Annotations/MyAnno
        27: invokevirtual #24                 // Method java/lang/reflect/Method.getAnnotation:(Ljava/lang/Class;)Ljava/lang/annotation/Annotation;
        30: checkcast     #22                 // class e0082_Annotations/MyAnno
        33: astore_3

        34: getstatic     #30                 // Field java/lang/System.out:Ljava/io/PrintStream;
        37: aload_3
        38: invokeinterface #36,  1           // InterfaceMethod e0082_Annotations/MyAnno.str:()Ljava/lang/String;
        43: aload_3
        44: invokeinterface #40,  1           // InterfaceMethod e0082_Annotations/MyAnno.val:()I
        49: invokedynamic #44,  0             // InvokeDynamic #0:makeConcatWithConstants:(Ljava/lang/String;I)Ljava/lang/String;
        54: invokevirtual #48                 // Method java/io/PrintStream.println:(Ljava/lang/String;)V
        57: goto          65
        
        60: astore_1
        61: aload_1
        62: invokevirtual #56                 // Method java/lang/NoSuchMethodException.printStackTrace:()V
        
        65: return
      Exception table:
         from    to  target type
             8    57    60   Class java/lang/NoSuchMethodException
      LineNumberTable:
        line 8: 0
        line 11: 8
        line 12: 13
        line 14: 24
        line 16: 34
        line 20: 57
        line 18: 60
        line 19: 61
        line 21: 65
      LocalVariableTable:
        Start  Length  Slot  Name   Signature
           13      44     1    cl   Ljava/lang/Class;
           24      33     2  meth   Ljava/lang/reflect/Method;
           34      23     3  anno   Le0082_Annotations/MyAnno;
           61       4     1     e   Ljava/lang/NoSuchMethodException;
            8      58     0    ob   Le0082_Annotations/Meta;
      LocalVariableTypeTable:
        Start  Length  Slot  Name   Signature
           13      44     1    cl   Ljava/lang/Class<*>;
      StackMapTable: number_of_entries = 2
        frame_type = 255 /* full_frame */ 
          offset_delta = 60
          locals = [ class e0082_Annotations/Meta ]
          stack = [ class java/lang/NoSuchMethodException ]
        frame_type = 4 /* same */ 
    RuntimeVisibleAnnotations:
      0: #71(#38=s#79,#42=I#80)
        e0082_Annotations.MyAnno(
          str="EXAMPLE ANNOTATION"
          val=111
        )

  public static void main(java.lang.String[]);
    descriptor: ([Ljava/lang/String;)V
    flags: (0x0009) ACC_PUBLIC, ACC_STATIC
    Code:
      stack=0, locals=1, args_size=1
         0: invokestatic  #59                 // Method myMeth:()V
         3: return
      LineNumberTable:
        line 24: 0
        line 25: 3
      LocalVariableTable:
        Start  Length  Slot  Name   Signature
            0       4     0  args   [Ljava/lang/String;
}
SourceFile: "Meta.java"
BootstrapMethods:
  0: #88 REF_invokeStatic java/lang/invoke/StringConcatFactory.makeConcatWithConstants:(Ljava/lang/invoke/MethodHandles$Lookup;Ljava/lang/String;Ljava/lang/invoke/MethodType;Ljava/lang/String;[Ljava/lang/Object;)Ljava/lang/invoke/CallSite;
    Method arguments:
      #94 \u0001 \u0001
InnerClasses:
  public static final #101= #97 of #99;   // Lookup=class java/lang/invoke/MethodHandles$Lookup of class java/lang/invoke/MethodHandles
#############################################################################################
package e0082_Annotations;

import java.lang.reflect.Method;

public class Meta {
    @MyAnno(str = "EXAMPLE ANNOTATION", val = 111)
    public static void myMeth() {
        Meta ob = new Meta();

        try {
            Class<?> cl = ob.getClass();
            Method meth = cl.getMethod("myMeth");

            MyAnno anno = meth.getAnnotation(MyAnno.class);

            System.out.println(anno.str() + " " + anno.val());

        } catch (NoSuchMethodException e) {
            e.printStackTrace();
        }
    }

    public static void main(String[] args) {
        myMeth();
    }
}
---------------------------------------------------------------------------------------------
