Classfile /E:/__PROJECT__/JAVA/BookShildt_002/out/production/BookShildt_002/e0070_Threads_and_socket_try_block/StateLooker7.class
  Last modified 24 ���. 2023 �.; size 3296 bytes
  SHA-256 checksum 91982009463f03ead9a360e74d3924c12ee29037234bd5a3f59cb55de257ea3d
  Compiled from "StateLooker7.java"
public class e0070_Threads_and_socket_try_block.StateLooker7 extends java.lang.Thread
  minor version: 0
  major version: 61
  flags: (0x0021) ACC_PUBLIC, ACC_SUPER
  this_class: #11                         // e0070_Threads_and_socket_try_block/StateLooker7
  super_class: #2                         // java/lang/Thread
  interfaces: 0, fields: 3, methods: 5, attributes: 3
Constant pool:
    #1 = Methodref          #2.#3         // java/lang/Thread."<init>":()V
    #2 = Class              #4            // java/lang/Thread
    #3 = NameAndType        #5:#6         // "<init>":()V
    #4 = Utf8               java/lang/Thread
    #5 = Utf8               <init>
    #6 = Utf8               ()V
    #7 = Class              #8            // java/util/ArrayList
    #8 = Utf8               java/util/ArrayList
    #9 = Methodref          #7.#3         // java/util/ArrayList."<init>":()V
   #10 = Fieldref           #11.#12       // e0070_Threads_and_socket_try_block/StateLooker7.subscribers:Ljava/util/List;
   #11 = Class              #13           // e0070_Threads_and_socket_try_block/StateLooker7
   #12 = NameAndType        #14:#15       // subscribers:Ljava/util/List;
   #13 = Utf8               e0070_Threads_and_socket_try_block/StateLooker7
   #14 = Utf8               subscribers
   #15 = Utf8               Ljava/util/List;
   #16 = Fieldref           #11.#17       // e0070_Threads_and_socket_try_block/StateLooker7.monitor:Le0070_Threads_and_socket_try_block/Monitor7;
   #17 = NameAndType        #18:#19       // monitor:Le0070_Threads_and_socket_try_block/Monitor7;
   #18 = Utf8               monitor
   #19 = Utf8               Le0070_Threads_and_socket_try_block/Monitor7;
   #20 = Fieldref           #11.#21       // e0070_Threads_and_socket_try_block/StateLooker7.name:Ljava/lang/String;
   #21 = NameAndType        #22:#23       // name:Ljava/lang/String;
   #22 = Utf8               name
   #23 = Utf8               Ljava/lang/String;
   #24 = Methodref          #11.#25       // e0070_Threads_and_socket_try_block/StateLooker7.setName:(Ljava/lang/String;)V
   #25 = NameAndType        #26:#27       // setName:(Ljava/lang/String;)V
   #26 = Utf8               setName
   #27 = Utf8               (Ljava/lang/String;)V
   #28 = InvokeDynamic      #0:#29        // #0:accept:(Le0070_Threads_and_socket_try_block/StateLooker7;)Ljava/util/function/Consumer;
   #29 = NameAndType        #30:#31       // accept:(Le0070_Threads_and_socket_try_block/StateLooker7;)Ljava/util/function/Consumer;
   #30 = Utf8               accept
   #31 = Utf8               (Le0070_Threads_and_socket_try_block/StateLooker7;)Ljava/util/function/Consumer;
   #32 = InterfaceMethodref #33.#34       // java/util/List.forEach:(Ljava/util/function/Consumer;)V
   #33 = Class              #35           // java/util/List
   #34 = NameAndType        #36:#37       // forEach:(Ljava/util/function/Consumer;)V
   #35 = Utf8               java/util/List
   #36 = Utf8               forEach
   #37 = Utf8               (Ljava/util/function/Consumer;)V
   #38 = Fieldref           #39.#40       // java/lang/System.out:Ljava/io/PrintStream;
   #39 = Class              #41           // java/lang/System
   #40 = NameAndType        #42:#43       // out:Ljava/io/PrintStream;
   #41 = Utf8               java/lang/System
   #42 = Utf8               out
   #43 = Utf8               Ljava/io/PrintStream;
   #44 = String             #45           // %s : %s : %s  was created...\n
   #45 = Utf8               %s : %s : %s  was created...\n
   #46 = Class              #47           // java/lang/Object
   #47 = Utf8               java/lang/Object
   #48 = Methodref          #11.#49       // e0070_Threads_and_socket_try_block/StateLooker7.getName:()Ljava/lang/String;
   #49 = NameAndType        #50:#51       // getName:()Ljava/lang/String;
   #50 = Utf8               getName
   #51 = Utf8               ()Ljava/lang/String;
   #52 = Methodref          #11.#53       // e0070_Threads_and_socket_try_block/StateLooker7.getPriority:()I
   #53 = NameAndType        #54:#55       // getPriority:()I
   #54 = Utf8               getPriority
   #55 = Utf8               ()I
   #56 = Methodref          #57.#58       // java/lang/Integer.valueOf:(I)Ljava/lang/Integer;
   #57 = Class              #59           // java/lang/Integer
   #58 = NameAndType        #60:#61       // valueOf:(I)Ljava/lang/Integer;
   #59 = Utf8               java/lang/Integer
   #60 = Utf8               valueOf
   #61 = Utf8               (I)Ljava/lang/Integer;
   #62 = Methodref          #11.#63       // e0070_Threads_and_socket_try_block/StateLooker7.getState:()Ljava/lang/Thread$State;
   #63 = NameAndType        #64:#65       // getState:()Ljava/lang/Thread$State;
   #64 = Utf8               getState
   #65 = Utf8               ()Ljava/lang/Thread$State;
   #66 = Methodref          #67.#68       // java/io/PrintStream.printf:(Ljava/lang/String;[Ljava/lang/Object;)Ljava/io/PrintStream;
   #67 = Class              #69           // java/io/PrintStream
   #68 = NameAndType        #70:#71       // printf:(Ljava/lang/String;[Ljava/lang/Object;)Ljava/io/PrintStream;
   #69 = Utf8               java/io/PrintStream
   #70 = Utf8               printf
   #71 = Utf8               (Ljava/lang/String;[Ljava/lang/Object;)Ljava/io/PrintStream;
   #72 = String             #73           // \nFrom %s .run() : %s was created...\n
   #73 = Utf8               \nFrom %s .run() : %s was created...\n
   #74 = InterfaceMethodref #33.#75       // java/util/List.get:(I)Ljava/lang/Object;
   #75 = NameAndType        #76:#77       // get:(I)Ljava/lang/Object;
   #76 = Utf8               get
   #77 = Utf8               (I)Ljava/lang/Object;
   #78 = Methodref          #2.#79        // java/lang/Thread.isAlive:()Z
   #79 = NameAndType        #80:#81       // isAlive:()Z
   #80 = Utf8               isAlive
   #81 = Utf8               ()Z
   #82 = InvokeDynamic      #1:#29        // #1:accept:(Le0070_Threads_and_socket_try_block/StateLooker7;)Ljava/util/function/Consumer;
   #83 = InvokeDynamic      #2:#29        // #2:accept:(Le0070_Threads_and_socket_try_block/StateLooker7;)Ljava/util/function/Consumer;
   #84 = String             #85           // %s sais: %s , %s\n
   #85 = Utf8               %s sais: %s , %s\n
   #86 = Methodref          #2.#49        // java/lang/Thread.getName:()Ljava/lang/String;
   #87 = Methodref          #2.#63        // java/lang/Thread.getState:()Ljava/lang/Thread$State;
   #88 = Long               100l
   #90 = Methodref          #2.#91        // java/lang/Thread.sleep:(J)V
   #91 = NameAndType        #92:#93       // sleep:(J)V
   #92 = Utf8               sleep
   #93 = Utf8               (J)V
   #94 = Class              #95           // java/lang/InterruptedException
   #95 = Utf8               java/lang/InterruptedException
   #96 = Methodref          #94.#97       // java/lang/InterruptedException.printStackTrace:()V
   #97 = NameAndType        #98:#6        // printStackTrace:()V
   #98 = Utf8               printStackTrace
   #99 = InterfaceMethodref #33.#100      // java/util/List.add:(Ljava/lang/Object;)Z
  #100 = NameAndType        #101:#102     // add:(Ljava/lang/Object;)Z
  #101 = Utf8               add
  #102 = Utf8               (Ljava/lang/Object;)Z
  #103 = String             #104          // \nfrom constructor StateLooker1 : %s : %s\n
  #104 = Utf8               \nfrom constructor StateLooker1 : %s : %s\n
  #105 = Utf8               Signature
  #106 = Utf8               Ljava/util/List<Ljava/lang/Thread;>;
  #107 = Utf8               (Ljava/lang/String;Ljava/util/List;Le0070_Threads_and_socket_try_block/Monitor7;)V
  #108 = Utf8               Code
  #109 = Utf8               LineNumberTable
  #110 = Utf8               LocalVariableTable
  #111 = Utf8               this
  #112 = Utf8               Le0070_Threads_and_socket_try_block/StateLooker7;
  #113 = Utf8               n
  #114 = Utf8               threads
  #115 = Utf8               m
  #116 = Utf8               LocalVariableTypeTable
  #117 = Utf8               (Ljava/lang/String;Ljava/util/List<Ljava/lang/Thread;>;Le0070_Threads_and_socket_try_block/Monitor7;)V
  #118 = Utf8               run
  #119 = Utf8               StackMapTable
  #120 = Utf8               lambda$run$2
  #121 = Utf8               (Ljava/lang/Thread;)V
  #122 = Utf8               e
  #123 = Utf8               Ljava/lang/InterruptedException;
  #124 = Utf8               s
  #125 = Utf8               Ljava/lang/Thread;
  #126 = Utf8               lambda$run$1
  #127 = Utf8               lambda$new$0
  #128 = Utf8               th
  #129 = Utf8               SourceFile
  #130 = Utf8               StateLooker7.java
  #131 = Utf8               BootstrapMethods
  #132 = MethodHandle       6:#133        // REF_invokeStatic java/lang/invoke/LambdaMetafactory.metafactory:(Ljava/lang/invoke/MethodHandles$Lookup;Ljava/lang/String;Ljava/lang/invoke/MethodType;Ljava/lang/invoke/MethodType;Ljava/lang/invoke/MethodHandle;Ljava/lang/invoke/MethodType;)Ljava/lang/invoke/CallSite;
  #133 = Methodref          #134.#135     // java/lang/invoke/LambdaMetafactory.metafactory:(Ljava/lang/invoke/MethodHandles$Lookup;Ljava/lang/String;Ljava/lang/invoke/MethodType;Ljava/lang/invoke/MethodType;Ljava/lang/invoke/MethodHandle;Ljava/lang/invoke/MethodType;)Ljava/lang/invoke/CallSite;
  #134 = Class              #136          // java/lang/invoke/LambdaMetafactory
  #135 = NameAndType        #137:#138     // metafactory:(Ljava/lang/invoke/MethodHandles$Lookup;Ljava/lang/String;Ljava/lang/invoke/MethodType;Ljava/lang/invoke/MethodType;Ljava/lang/invoke/MethodHandle;Ljava/lang/invoke/MethodType;)Ljava/lang/invoke/CallSite;
  #136 = Utf8               java/lang/invoke/LambdaMetafactory
  #137 = Utf8               metafactory
  #138 = Utf8               (Ljava/lang/invoke/MethodHandles$Lookup;Ljava/lang/String;Ljava/lang/invoke/MethodType;Ljava/lang/invoke/MethodType;Ljava/lang/invoke/MethodHandle;Ljava/lang/invoke/MethodType;)Ljava/lang/invoke/CallSite;
  #139 = MethodType         #140          //  (Ljava/lang/Object;)V
  #140 = Utf8               (Ljava/lang/Object;)V
  #141 = MethodHandle       5:#142        // REF_invokeVirtual e0070_Threads_and_socket_try_block/StateLooker7.lambda$new$0:(Ljava/lang/Thread;)V
  #142 = Methodref          #11.#143      // e0070_Threads_and_socket_try_block/StateLooker7.lambda$new$0:(Ljava/lang/Thread;)V
  #143 = NameAndType        #127:#121     // lambda$new$0:(Ljava/lang/Thread;)V
  #144 = MethodType         #121          //  (Ljava/lang/Thread;)V
  #145 = MethodHandle       5:#146        // REF_invokeVirtual e0070_Threads_and_socket_try_block/StateLooker7.lambda$run$1:(Ljava/lang/Thread;)V
  #146 = Methodref          #11.#147      // e0070_Threads_and_socket_try_block/StateLooker7.lambda$run$1:(Ljava/lang/Thread;)V
  #147 = NameAndType        #126:#121     // lambda$run$1:(Ljava/lang/Thread;)V
  #148 = MethodHandle       5:#149        // REF_invokeVirtual e0070_Threads_and_socket_try_block/StateLooker7.lambda$run$2:(Ljava/lang/Thread;)V
  #149 = Methodref          #11.#150      // e0070_Threads_and_socket_try_block/StateLooker7.lambda$run$2:(Ljava/lang/Thread;)V
  #150 = NameAndType        #120:#121     // lambda$run$2:(Ljava/lang/Thread;)V
  #151 = Utf8               InnerClasses
  #152 = Class              #153          // java/lang/Thread$State
  #153 = Utf8               java/lang/Thread$State
  #154 = Utf8               State
  #155 = Class              #156          // java/lang/invoke/MethodHandles$Lookup
  #156 = Utf8               java/lang/invoke/MethodHandles$Lookup
  #157 = Class              #158          // java/lang/invoke/MethodHandles
  #158 = Utf8               java/lang/invoke/MethodHandles
  #159 = Utf8               Lookup
{
  java.lang.String name;
    descriptor: Ljava/lang/String;
    flags: (0x0000)

  java.util.List<java.lang.Thread> subscribers;
    descriptor: Ljava/util/List;
    flags: (0x0000)
    Signature: #106                         // Ljava/util/List<Ljava/lang/Thread;>;

  e0070_Threads_and_socket_try_block.Monitor7 monitor;
    descriptor: Le0070_Threads_and_socket_try_block/Monitor7;
    flags: (0x0000)

  e0070_Threads_and_socket_try_block.StateLooker7(java.lang.String, java.util.List<java.lang.Thread>, e0070_Threads_and_socket_try_block.Monitor7);
    descriptor: (Ljava/lang/String;Ljava/util/List;Le0070_Threads_and_socket_try_block/Monitor7;)V
    flags: (0x0000)
    Code:
      stack=6, locals=4, args_size=4
         0: aload_0
         1: invokespecial #1                  // Method java/lang/Thread."<init>":()V
         4: aload_0
         5: new           #7                  // class java/util/ArrayList
         8: dup
         9: invokespecial #9                  // Method java/util/ArrayList."<init>":()V
        12: putfield      #10                 // Field subscribers:Ljava/util/List;
        15: aload_0
        16: aload_3
        17: putfield      #16                 // Field monitor:Le0070_Threads_and_socket_try_block/Monitor7;
        20: aload_0
        21: aload_1
        22: putfield      #20                 // Field name:Ljava/lang/String;
        25: aload_0
        26: aload_0
        27: getfield      #20                 // Field name:Ljava/lang/String;
        30: invokevirtual #24                 // Method setName:(Ljava/lang/String;)V
        33: aload_2
        34: aload_0
        35: invokedynamic #28,  0             // InvokeDynamic #0:accept:(Le0070_Threads_and_socket_try_block/StateLooker7;)Ljava/util/function/Consumer;
        40: invokeinterface #32,  2           // InterfaceMethod java/util/List.forEach:(Ljava/util/function/Consumer;)V
        45: getstatic     #38                 // Field java/lang/System.out:Ljava/io/PrintStream;
        48: ldc           #44                 // String %s : %s : %s  was created...\n
        50: iconst_3
        51: anewarray     #46                 // class java/lang/Object
        54: dup
        55: iconst_0
        56: aload_0
        57: invokevirtual #48                 // Method getName:()Ljava/lang/String;
        60: aastore
        61: dup
        62: iconst_1
        63: aload_0
        64: invokevirtual #52                 // Method getPriority:()I
        67: invokestatic  #56                 // Method java/lang/Integer.valueOf:(I)Ljava/lang/Integer;
        70: aastore
        71: dup
        72: iconst_2
        73: aload_0
        74: invokevirtual #62                 // Method getState:()Ljava/lang/Thread$State;
        77: aastore
        78: invokevirtual #66                 // Method java/io/PrintStream.printf:(Ljava/lang/String;[Ljava/lang/Object;)Ljava/io/PrintStream;
        81: pop
        82: return
      LineNumberTable:
        line 13: 0
        line 9: 4
        line 14: 15
        line 15: 20
        line 16: 25
        line 17: 33
        line 22: 45
        line 23: 82
      LocalVariableTable:
        Start  Length  Slot  Name   Signature
            0      83     0  this   Le0070_Threads_and_socket_try_block/StateLooker7;
            0      83     1     n   Ljava/lang/String;
            0      83     2 threads   Ljava/util/List;
            0      83     3     m   Le0070_Threads_and_socket_try_block/Monitor7;
      LocalVariableTypeTable:
        Start  Length  Slot  Name   Signature
            0      83     2 threads   Ljava/util/List<Ljava/lang/Thread;>;
    Signature: #117                         // (Ljava/lang/String;Ljava/util/List<Ljava/lang/Thread;>;Le0070_Threads_and_socket_try_block/Monitor7;)V

  public void run();
    descriptor: ()V
    flags: (0x0001) ACC_PUBLIC
    Code:
      stack=6, locals=1, args_size=1
         0: getstatic     #38                 // Field java/lang/System.out:Ljava/io/PrintStream;
         3: ldc           #72                 // String \nFrom %s .run() : %s was created...\n
         5: iconst_2
         6: anewarray     #46                 // class java/lang/Object
         9: dup
        10: iconst_0
        11: aload_0
        12: getfield      #20                 // Field name:Ljava/lang/String;
        15: aastore
        16: dup
        17: iconst_1
        18: aload_0
        19: invokevirtual #62                 // Method getState:()Ljava/lang/Thread$State;
        22: aastore
        23: invokevirtual #66                 // Method java/io/PrintStream.printf:(Ljava/lang/String;[Ljava/lang/Object;)Ljava/io/PrintStream;
        26: pop
        27: aload_0
        28: getfield      #10                 // Field subscribers:Ljava/util/List;
        31: iconst_0
        32: invokeinterface #74,  2           // InterfaceMethod java/util/List.get:(I)Ljava/lang/Object;
        37: checkcast     #2                  // class java/lang/Thread
        40: invokevirtual #78                 // Method java/lang/Thread.isAlive:()Z
        43: ifeq          64
        46: aload_0
        47: getfield      #10                 // Field subscribers:Ljava/util/List;
        50: aload_0
        51: invokedynamic #82,  0             // InvokeDynamic #1:accept:(Le0070_Threads_and_socket_try_block/StateLooker7;)Ljava/util/function/Consumer;
        56: invokeinterface #32,  2           // InterfaceMethod java/util/List.forEach:(Ljava/util/function/Consumer;)V
        61: goto          27
        64: aload_0
        65: getfield      #10                 // Field subscribers:Ljava/util/List;
        68: aload_0
        69: invokedynamic #83,  0             // InvokeDynamic #2:accept:(Le0070_Threads_and_socket_try_block/StateLooker7;)Ljava/util/function/Consumer;
        74: invokeinterface #32,  2           // InterfaceMethod java/util/List.forEach:(Ljava/util/function/Consumer;)V
        79: return
      LineNumberTable:
        line 28: 0
        line 30: 27
        line 31: 46
        line 41: 64
        line 50: 79
      LocalVariableTable:
        Start  Length  Slot  Name   Signature
            0      80     0  this   Le0070_Threads_and_socket_try_block/StateLooker7;
      StackMapTable: number_of_entries = 2
        frame_type = 27 /* same */ 
        frame_type = 36 /* same */ 
}
SourceFile: "StateLooker7.java"
BootstrapMethods:
  0: #132 REF_invokeStatic java/lang/invoke/LambdaMetafactory.metafactory:(Ljava/lang/invoke/MethodHandles$Lookup;Ljava/lang/String;Ljava/lang/invoke/MethodType;Ljava/lang/invoke/MethodType;Ljava/lang/invoke/MethodHandle;Ljava/lang/invoke/MethodType;)Ljava/lang/invoke/CallSite;
    Method arguments:
      #139 (Ljava/lang/Object;)V
      #141 REF_invokeVirtual e0070_Threads_and_socket_try_block/StateLooker7.lambda$new$0:(Ljava/lang/Thread;)V
      #144 (Ljava/lang/Thread;)V
  1: #132 REF_invokeStatic java/lang/invoke/LambdaMetafactory.metafactory:(Ljava/lang/invoke/MethodHandles$Lookup;Ljava/lang/String;Ljava/lang/invoke/MethodType;Ljava/lang/invoke/MethodType;Ljava/lang/invoke/MethodHandle;Ljava/lang/invoke/MethodType;)Ljava/lang/invoke/CallSite;
    Method arguments:
      #139 (Ljava/lang/Object;)V
      #145 REF_invokeVirtual e0070_Threads_and_socket_try_block/StateLooker7.lambda$run$1:(Ljava/lang/Thread;)V
      #144 (Ljava/lang/Thread;)V
  2: #132 REF_invokeStatic java/lang/invoke/LambdaMetafactory.metafactory:(Ljava/lang/invoke/MethodHandles$Lookup;Ljava/lang/String;Ljava/lang/invoke/MethodType;Ljava/lang/invoke/MethodType;Ljava/lang/invoke/MethodHandle;Ljava/lang/invoke/MethodType;)Ljava/lang/invoke/CallSite;
    Method arguments:
      #139 (Ljava/lang/Object;)V
      #148 REF_invokeVirtual e0070_Threads_and_socket_try_block/StateLooker7.lambda$run$2:(Ljava/lang/Thread;)V
      #144 (Ljava/lang/Thread;)V
InnerClasses:
  public static final #154= #152 of #2;   // State=class java/lang/Thread$State of class java/lang/Thread
  public static final #159= #155 of #157; // Lookup=class java/lang/invoke/MethodHandles$Lookup of class java/lang/invoke/MethodHandles
#############################################################################################
package e0070_Threads_and_socket_try_block;


import java.util.ArrayList;
import java.util.List;

public class StateLooker7 extends Thread{
    String name;
    List<Thread> subscribers = new ArrayList<>();
    Monitor7 monitor;


    StateLooker7(String n, List<Thread> threads, Monitor7 m) {
        monitor = m;
        name = n;
        setName(name);
        threads.forEach(th -> {
            subscribers.add(th);
            System.out.printf("\nfrom constructor StateLooker1 : %s : %s\n", th.getName(), th.getState());
        });

        System.out.printf("%s : %s : %s  was created...\n", getName(), getPriority(), getState());
    }


    @Override
    public void run() {
        System.out.printf("\nFrom %s .run() : %s was created...\n", name, getState());

        while (subscribers.get(0).isAlive()) {
            subscribers.forEach(s -> {
                System.out.printf("%s sais: %s , %s\n", name, s.getName(), s.getState());
                try {
                    Thread.sleep(100);
                } catch (InterruptedException e) {
                    e.printStackTrace();
                }
            });
        }

        subscribers.forEach(s -> {
            System.out.printf("%s sais: %s , %s\n", name, s.getName(), s.getState());
            try {
                Thread.sleep(100);
            } catch (InterruptedException e) {
                e.printStackTrace();
            }
        });

    }
}
---------------------------------------------------------------------------------------------
