Classfile /E:/__PROJECT__/JAVA/BookShildt_002/out/production/BookShildt_002/e0091_Type_Templates/GenDemo.class
  Last modified 8 ����. 2023 �.; size 1710 bytes
  SHA-256 checksum 9357ebc5f665c435bbd0a2ab2e5508cb79ba7702ed2e886b0138d0a5bb6d8e4a
  Compiled from "GenDemo.java"
public class e0091_Type_Templates.GenDemo
  minor version: 0
  major version: 61
  flags: (0x0021) ACC_PUBLIC, ACC_SUPER
  this_class: #54                         // e0091_Type_Templates/GenDemo
  super_class: #2                         // java/lang/Object
  interfaces: 0, fields: 0, methods: 2, attributes: 3
Constant pool:
   #1 = Methodref          #2.#3          // java/lang/Object."<init>":()V
   #2 = Class              #4             // java/lang/Object
   #3 = NameAndType        #5:#6          // "<init>":()V
   #4 = Utf8               java/lang/Object
   #5 = Utf8               <init>
   #6 = Utf8               ()V
   #7 = Class              #8             // e0091_Type_Templates/Gen
   #8 = Utf8               e0091_Type_Templates/Gen
   #9 = Methodref          #10.#11        // java/lang/Integer.valueOf:(I)Ljava/lang/Integer;
  #10 = Class              #12            // java/lang/Integer
  #11 = NameAndType        #13:#14        // valueOf:(I)Ljava/lang/Integer;
  #12 = Utf8               java/lang/Integer
  #13 = Utf8               valueOf
  #14 = Utf8               (I)Ljava/lang/Integer;
  #15 = Methodref          #7.#16         // e0091_Type_Templates/Gen."<init>":(Ljava/lang/Object;)V
  #16 = NameAndType        #5:#17         // "<init>":(Ljava/lang/Object;)V
  #17 = Utf8               (Ljava/lang/Object;)V
  #18 = Methodref          #7.#19         // e0091_Type_Templates/Gen.showType:()V
  #19 = NameAndType        #20:#6         // showType:()V
  #20 = Utf8               showType
  #21 = Methodref          #7.#22         // e0091_Type_Templates/Gen.getOb:()Ljava/lang/Object;
  #22 = NameAndType        #23:#24        // getOb:()Ljava/lang/Object;
  #23 = Utf8               getOb
  #24 = Utf8               ()Ljava/lang/Object;
  #25 = Methodref          #10.#26        // java/lang/Integer.intValue:()I
  #26 = NameAndType        #27:#28        // intValue:()I
  #27 = Utf8               intValue
  #28 = Utf8               ()I
  #29 = Fieldref           #30.#31        // java/lang/System.out:Ljava/io/PrintStream;
  #30 = Class              #32            // java/lang/System
  #31 = NameAndType        #33:#34        // out:Ljava/io/PrintStream;
  #32 = Utf8               java/lang/System
  #33 = Utf8               out
  #34 = Utf8               Ljava/io/PrintStream;
  #35 = InvokeDynamic      #0:#36         // #0:makeConcatWithConstants:(I)Ljava/lang/String;
  #36 = NameAndType        #37:#38        // makeConcatWithConstants:(I)Ljava/lang/String;
  #37 = Utf8               makeConcatWithConstants
  #38 = Utf8               (I)Ljava/lang/String;
  #39 = Methodref          #40.#41        // java/io/PrintStream.println:(Ljava/lang/String;)V
  #40 = Class              #42            // java/io/PrintStream
  #41 = NameAndType        #43:#44        // println:(Ljava/lang/String;)V
  #42 = Utf8               java/io/PrintStream
  #43 = Utf8               println
  #44 = Utf8               (Ljava/lang/String;)V
  #45 = Methodref          #40.#46        // java/io/PrintStream.println:()V
  #46 = NameAndType        #43:#6         // println:()V
  #47 = String             #48            // Some message
  #48 = Utf8               Some message
  #49 = Class              #50            // java/lang/String
  #50 = Utf8               java/lang/String
  #51 = InvokeDynamic      #1:#52         // #1:makeConcatWithConstants:(Ljava/lang/String;)Ljava/lang/String;
  #52 = NameAndType        #37:#53        // makeConcatWithConstants:(Ljava/lang/String;)Ljava/lang/String;
  #53 = Utf8               (Ljava/lang/String;)Ljava/lang/String;
  #54 = Class              #55            // e0091_Type_Templates/GenDemo
  #55 = Utf8               e0091_Type_Templates/GenDemo
  #56 = Utf8               Code
  #57 = Utf8               LineNumberTable
  #58 = Utf8               LocalVariableTable
  #59 = Utf8               this
  #60 = Utf8               Le0091_Type_Templates/GenDemo;
  #61 = Utf8               main
  #62 = Utf8               ([Ljava/lang/String;)V
  #63 = Utf8               args
  #64 = Utf8               [Ljava/lang/String;
  #65 = Utf8               iOb
  #66 = Utf8               Le0091_Type_Templates/Gen;
  #67 = Utf8               v
  #68 = Utf8               I
  #69 = Utf8               strOb
  #70 = Utf8               str
  #71 = Utf8               Ljava/lang/String;
  #72 = Utf8               LocalVariableTypeTable
  #73 = Utf8               Le0091_Type_Templates/Gen<Ljava/lang/Integer;>;
  #74 = Utf8               Le0091_Type_Templates/Gen<Ljava/lang/String;>;
  #75 = Utf8               SourceFile
  #76 = Utf8               GenDemo.java
  #77 = Utf8               BootstrapMethods
  #78 = MethodHandle       6:#79          // REF_invokeStatic java/lang/invoke/StringConcatFactory.makeConcatWithConstants:(Ljava/lang/invoke/MethodHandles$Lookup;Ljava/lang/String;Ljava/lang/invoke/MethodType;Ljava/lang/String;[Ljava/lang/Object;)Ljava/lang/invoke/CallSite;
  #79 = Methodref          #80.#81        // java/lang/invoke/StringConcatFactory.makeConcatWithConstants:(Ljava/lang/invoke/MethodHandles$Lookup;Ljava/lang/String;Ljava/lang/invoke/MethodType;Ljava/lang/String;[Ljava/lang/Object;)Ljava/lang/invoke/CallSite;
  #80 = Class              #82            // java/lang/invoke/StringConcatFactory
  #81 = NameAndType        #37:#83        // makeConcatWithConstants:(Ljava/lang/invoke/MethodHandles$Lookup;Ljava/lang/String;Ljava/lang/invoke/MethodType;Ljava/lang/String;[Ljava/lang/Object;)Ljava/lang/invoke/CallSite;
  #82 = Utf8               java/lang/invoke/StringConcatFactory
  #83 = Utf8               (Ljava/lang/invoke/MethodHandles$Lookup;Ljava/lang/String;Ljava/lang/invoke/MethodType;Ljava/lang/String;[Ljava/lang/Object;)Ljava/lang/invoke/CallSite;
  #84 = String             #85            // Value v: \u0001
  #85 = Utf8               Value v: \u0001
  #86 = String             #87            // Value str: \u0001
  #87 = Utf8               Value str: \u0001
  #88 = Utf8               InnerClasses
  #89 = Class              #90            // java/lang/invoke/MethodHandles$Lookup
  #90 = Utf8               java/lang/invoke/MethodHandles$Lookup
  #91 = Class              #92            // java/lang/invoke/MethodHandles
  #92 = Utf8               java/lang/invoke/MethodHandles
  #93 = Utf8               Lookup
{
  public e0091_Type_Templates.GenDemo();
    descriptor: ()V
    flags: (0x0001) ACC_PUBLIC
    Code:
      stack=1, locals=1, args_size=1
         0: aload_0
         1: invokespecial #1                  // Method java/lang/Object."<init>":()V
         4: return
      LineNumberTable:
        line 3: 0
      LocalVariableTable:
        Start  Length  Slot  Name   Signature
            0       5     0  this   Le0091_Type_Templates/GenDemo;

  public static void main(java.lang.String[]);
    descriptor: ([Ljava/lang/String;)V
    flags: (0x0009) ACC_PUBLIC, ACC_STATIC
    Code:
      stack=3, locals=5, args_size=1
         0: new           #7                  // class e0091_Type_Templates/Gen
         3: dup
         4: bipush        88
         6: invokestatic  #9                  // Method java/lang/Integer.valueOf:(I)Ljava/lang/Integer;
         9: invokespecial #15                 // Method e0091_Type_Templates/Gen."<init>":(Ljava/lang/Object;)V
        12: astore_1
        
        13: aload_1
        14: invokevirtual #18                 // Method e0091_Type_Templates/Gen.showType:()V
        17: aload_1
        18: invokevirtual #21                 // Method e0091_Type_Templates/Gen.getOb:()Ljava/lang/Object;
        21: checkcast     #10                 // class java/lang/Integer
        24: invokevirtual #25                 // Method java/lang/Integer.intValue:()I
        27: istore_2

        28: getstatic     #29                 // Field java/lang/System.out:Ljava/io/PrintStream;
        31: iload_2
        32: invokedynamic #35,  0             // InvokeDynamic #0:makeConcatWithConstants:(I)Ljava/lang/String;
        37: invokevirtual #39                 // Method java/io/PrintStream.println:(Ljava/lang/String;)V
        40: getstatic     #29                 // Field java/lang/System.out:Ljava/io/PrintStream;
        43: invokevirtual #45                 // Method java/io/PrintStream.println:()V
        
        46: new           #7                  // class e0091_Type_Templates/Gen
        49: dup
        50: ldc           #47                 // String Some message
        52: invokespecial #15                 // Method e0091_Type_Templates/Gen."<init>":(Ljava/lang/Object;)V
        55: astore_3
        
        56: aload_3
        57: invokevirtual #18                 // Method e0091_Type_Templates/Gen.showType:()V
        60: aload_3
        61: invokevirtual #21                 // Method e0091_Type_Templates/Gen.getOb:()Ljava/lang/Object;
        64: checkcast     #49                 // class java/lang/String
        67: astore        4
        
        69: getstatic     #29                 // Field java/lang/System.out:Ljava/io/PrintStream;
        72: aload         4
        74: invokedynamic #51,  0             // InvokeDynamic #1:makeConcatWithConstants:(Ljava/lang/String;)Ljava/lang/String;
        79: invokevirtual #39                 // Method java/io/PrintStream.println:(Ljava/lang/String;)V
        82: return
      LineNumberTable:
        line 7: 0
        line 9: 13
        line 11: 17
        line 12: 28
        line 13: 40
        line 15: 46
        line 16: 56
        line 18: 60
        line 19: 69
        line 20: 82
      LocalVariableTable:
        Start  Length  Slot  Name   Signature
            0      83     0  args   [Ljava/lang/String;
           13      70     1   iOb   Le0091_Type_Templates/Gen;
           28      55     2     v   I
           56      27     3 strOb   Le0091_Type_Templates/Gen;
           69      14     4   str   Ljava/lang/String;
      LocalVariableTypeTable:
        Start  Length  Slot  Name   Signature
           13      70     1   iOb   Le0091_Type_Templates/Gen<Ljava/lang/Integer;>;
           56      27     3 strOb   Le0091_Type_Templates/Gen<Ljava/lang/String;>;
}
SourceFile: "GenDemo.java"
BootstrapMethods:
  0: #78 REF_invokeStatic java/lang/invoke/StringConcatFactory.makeConcatWithConstants:(Ljava/lang/invoke/MethodHandles$Lookup;Ljava/lang/String;Ljava/lang/invoke/MethodType;Ljava/lang/String;[Ljava/lang/Object;)Ljava/lang/invoke/CallSite;
    Method arguments:
      #84 Value v: \u0001
  1: #78 REF_invokeStatic java/lang/invoke/StringConcatFactory.makeConcatWithConstants:(Ljava/lang/invoke/MethodHandles$Lookup;Ljava/lang/String;Ljava/lang/invoke/MethodType;Ljava/lang/String;[Ljava/lang/Object;)Ljava/lang/invoke/CallSite;
    Method arguments:
      #86 Value str: \u0001
InnerClasses:
  public static final #93= #89 of #91;    // Lookup=class java/lang/invoke/MethodHandles$Lookup of class java/lang/invoke/MethodHandles
#############################################################################################
package e0091_Type_Templates;

public class GenDemo {
    public static void main(String[] args) {
        Gen<Integer> iOb;

        iOb = new Gen<Integer>(88);

        iOb.showType();

        int v = iOb.getOb();
        System.out.println("Value v: " + v);
        System.out.println();

        Gen<String> strOb = new Gen<String>("Some message");
        strOb.showType();

        String str = strOb.getOb();
        System.out.println("Value str: " + str);
    }
}
---------------------------------------------------------------------------------------------
